radiens/__init__.py
radiens/allego_client.py
radiens/curate_client.py
radiens/file_sys_client.py
radiens/metrics_client.py
radiens/signals_client.py
radiens/spike_sorter_client.py
radiens/spikes_client.py
radiens/version.py
radiens/videre_client.py
radiens/workspace_client.py
radiens/api/__init__.py
radiens/api/api_allego.py
radiens/api/api_curate.py
radiens/api/api_videre.py
radiens/api/api_utils/__init__.py
radiens/api/api_utils/protocols.py
radiens/api/api_utils/util.py
radiens/auth/__init__.py
radiens/auth/interceptors.py
radiens/cli/__init__.py
radiens/cli/allego.py
radiens/cli/file_sys.py
radiens/cli/main.py
radiens/cli/signal_metrics.py
radiens/cli/signals.py
radiens/cli/spike_sorter.py
radiens/cli/sys.py
radiens/cli/videre.py
radiens/exceptions/__init__.py
radiens/exceptions/grpc_error.py
radiens/exceptions/scan_for_server_error.py
radiens/grpc_radiens/__init__.py
radiens/grpc_radiens/allegoserver_pb2.py
radiens/grpc_radiens/allegoserver_pb2.pyi
radiens/grpc_radiens/allegoserver_pb2_grpc.py
radiens/grpc_radiens/allegoserver_pb2_grpc.pyi
radiens/grpc_radiens/biointerface_pb2.py
radiens/grpc_radiens/biointerface_pb2.pyi
radiens/grpc_radiens/biointerface_pb2_grpc.py
radiens/grpc_radiens/biointerface_pb2_grpc.pyi
radiens/grpc_radiens/common_pb2.py
radiens/grpc_radiens/common_pb2.pyi
radiens/grpc_radiens/common_pb2_grpc.py
radiens/grpc_radiens/common_pb2_grpc.pyi
radiens/grpc_radiens/datasource_pb2.py
radiens/grpc_radiens/datasource_pb2.pyi
radiens/grpc_radiens/datasource_pb2_grpc.py
radiens/grpc_radiens/datasource_pb2_grpc.pyi
radiens/grpc_radiens/pybridge_pb2.py
radiens/grpc_radiens/pybridge_pb2.pyi
radiens/grpc_radiens/pybridge_pb2_grpc.py
radiens/grpc_radiens/pybridge_pb2_grpc.pyi
radiens/grpc_radiens/radiens_dev_pb2.py
radiens/grpc_radiens/radiens_dev_pb2.pyi
radiens/grpc_radiens/radiens_dev_pb2_grpc.py
radiens/grpc_radiens/radiens_dev_pb2_grpc.pyi
radiens/grpc_radiens/radiensserver_pb2.py
radiens/grpc_radiens/radiensserver_pb2.pyi
radiens-4.0.0.dist-info/LICENSE
radiens-4.0.0.dist-info/METADATA
radiens-4.0.0.dist-info/WHEEL
radiens-4.0.0.dist-info/entry_points.txt
radiens-4.0.0.dist-info/top_level.txt
radiens-4.0.0.dist-info/RECORD
