Metadata-Version: 2.1
Name: radiens
Version: 4.0.0
Summary: provides python API to RADIENS analytics platform
Home-page: http://neuronexus.github.io
Author: NeuroNexus
Author-email: dkipke@neuronexus.com
License: MIT
Classifier: Operating System :: OS Independent
Classifier: Programming Language :: Python :: 3.10
Classifier: License :: OSI Approved :: MIT License
Requires-Python: >=3.10
License-File: LICENSE
Requires-Dist: numpy ==2.2.6
Requires-Dist: boto3 ==1.34.49
Requires-Dist: pandas ==2.2.3
Requires-Dist: grpcio-tools ==1.71.0
Requires-Dist: grpc-interceptor ==0.15.4
Requires-Dist: tqdm ==4.65.0
Requires-Dist: click ==8.1.8
Requires-Dist: click-shell ==2.1
